<?xml version="1.0" encoding="UTF-8"?>
<sv:node sv:name="clProvider" xmlns:sv="http://www.jcp.org/jcr/sv/1.0" xmlns:xsi="http://www.w3.org/2001/XMLSchema-instance">
  <sv:property sv:name="jcr:primaryType" sv:type="Name">
    <sv:value>mgnl:contentNode</sv:value>
  </sv:property>
  <sv:property sv:name="jcr:uuid" sv:type="String">
    <sv:value>6ea854aa-8a00-43f9-9466-3fb37ff4d821</sv:value>
  </sv:property>
  <sv:property sv:name="class" sv:type="String">
    <sv:value>com.sharecare.cms.cloudinary.dam.CloudinaryAssetProvider</sv:value>
  </sv:property>
  <sv:property sv:name="identifier" sv:type="String">
    <sv:value>cl</sv:value>
  </sv:property>
  <sv:property sv:name="jcr:createdBy" sv:type="String">
    <sv:value>admin</sv:value>
  </sv:property>
  <sv:property sv:name="mgnl:created" sv:type="Date">
    <sv:value>2016-02-10T10:54:09.319-05:00</sv:value>
  </sv:property>
  <sv:property sv:name="mgnl:createdBy" sv:type="String">
    <sv:value>superuser</sv:value>
  </sv:property>
  <sv:property sv:name="mgnl:lastModified" sv:type="Date">
    <sv:value>2016-02-10T10:54:37.677-05:00</sv:value>
  </sv:property>
  <sv:property sv:name="mgnl:lastModifiedBy" sv:type="String">
    <sv:value>superuser</sv:value>
  </sv:property>
</sv:node>
